windowlicker/__init__.py
windowlicker-0.0.1.dist-info/METADATA
windowlicker-0.0.1.dist-info/WHEEL
windowlicker-0.0.1.dist-info/top_level.txt
windowlicker-0.0.1.dist-info/RECORD
