Metadata-Version: 2.4
Name: windowlicker
Version: 0.0.1
Summary: A cross-platform graphical library
Author-email: Warren Elrod <you@example.com>
License: MIT
Classifier: Programming Language :: Python :: 3
Classifier: License :: OSI Approved :: MIT License
Classifier: Operating System :: OS Independent
Requires-Python: >=3.10
